[
  {
    "type": "MAGAZINE",
    "id": "belt308",
    "copy-from": "belt308",
    "name": { "str": "7.62x51mm ammo belt" },
    "pocket_data": [
      {
        "pocket_type": "MAGAZINE",
        "rigid": true,
        "ammo_restriction": { "308": 500 },
        "max_contains_weight": "1000 kg",
        "max_item_length": "1 km"
      }
    ]
  },
  {
    "type": "MAGAZINE",
    "id": "falbigmag",
    "copy-from": "falbigmag",
    "name": { "str": "FAL 30-round magazine" },
    "pocket_data": [
      {
        "pocket_type": "MAGAZINE",
        "rigid": true,
        "ammo_restriction": { "308": 30 },
        "max_contains_weight": "1000 kg",
        "max_item_length": "1 km"
      }
    ]
  },
  {
    "type": "MAGAZINE",
    "id": "falmag",
    "copy-from": "falmag",
    "name": { "str": "FAL 20-round magazine" },
    "pocket_data": [
      {
        "pocket_type": "MAGAZINE",
        "rigid": true,
        "ammo_restriction": { "308": 20 },
        "max_contains_weight": "1000 kg",
        "max_item_length": "1 km"
      }
    ]
  },
  {
    "type": "MAGAZINE",
    "id": "fal_makeshiftmag",
    "copy-from": "fal_makeshiftmag",
    "name": { "str": "FAL 5-round makeshift magazine" },
    "pocket_data": [
      {
        "pocket_type": "MAGAZINE",
        "rigid": true,
        "ammo_restriction": { "308": 5 },
        "max_contains_weight": "1000 kg",
        "max_item_length": "1 km"
      }
    ]
  },
  {
    "type": "MAGAZINE",
    "id": "g3bigmag",
    "copy-from": "g3bigmag",
    "name": { "str": "G3 50-round drum magazine" },
    "pocket_data": [
      {
        "pocket_type": "MAGAZINE",
        "rigid": true,
        "ammo_restriction": { "308": 50 },
        "max_contains_weight": "1000 kg",
        "max_item_length": "1 km"
      }
    ]
  },
  {
    "type": "MAGAZINE",
    "id": "g3mag",
    "copy-from": "g3mag",
    "name": { "str": "G3 20-round magazine" },
    "pocket_data": [
      {
        "pocket_type": "MAGAZINE",
        "rigid": true,
        "ammo_restriction": { "308": 20 },
        "max_contains_weight": "1000 kg",
        "max_item_length": "1 km"
      }
    ]
  },
  {
    "type": "MAGAZINE",
    "id": "m14mag",
    "copy-from": "m14mag",
    "name": { "str": "M14 20-round magazine" },
    "pocket_data": [
      {
        "pocket_type": "MAGAZINE",
        "rigid": true,
        "ammo_restriction": { "308": 20 },
        "max_contains_weight": "1000 kg",
        "max_item_length": "1 km"
      }
    ]
  },
  {
    "type": "MAGAZINE",
    "id": "m14smallmag",
    "copy-from": "m14smallmag",
    "name": { "str": "M14 5-round magazine" },
    "pocket_data": [
      {
        "pocket_type": "MAGAZINE",
        "rigid": true,
        "ammo_restriction": { "308": 5 },
        "max_contains_weight": "1000 kg",
        "max_item_length": "1 km"
      }
    ]
  },
  {
    "type": "MAGAZINE",
    "id": "scarhbigmag",
    "copy-from": "scarhbigmag",
    "name": { "str": "SCAR-H 50-round drum magazine" },
    "pocket_data": [
      {
        "pocket_type": "MAGAZINE",
        "rigid": true,
        "ammo_restriction": { "308": 50 },
        "max_contains_weight": "1000 kg",
        "max_item_length": "1 km"
      }
    ]
  },
  {
    "type": "MAGAZINE",
    "id": "scarhmag",
    "copy-from": "scarhmag",
    "name": { "str": "SCAR-H 20-round magazine" },
    "pocket_data": [
      {
        "pocket_type": "MAGAZINE",
        "rigid": true,
        "ammo_restriction": { "308": 20 },
        "max_contains_weight": "1000 kg",
        "max_item_length": "1 km"
      }
    ]
  },
  {
    "type": "MAGAZINE",
    "id": "hk417mag_20rd",
    "copy-from": "hk417mag_20rd",
    "name": { "str": "HK417 20-round magazine" },
    "pocket_data": [
      {
        "pocket_type": "MAGAZINE",
        "rigid": true,
        "ammo_restriction": { "308": 20 },
        "max_contains_weight": "1000 kg",
        "max_item_length": "1 km"
      }
    ]
  },
  {
    "type": "MAGAZINE",
    "id": "hk417mag_10rd",
    "copy-from": "hk417mag_10rd",
    "name": { "str": "HK417 10-round magazine" },
    "pocket_data": [
      {
        "pocket_type": "MAGAZINE",
        "rigid": true,
        "ammo_restriction": { "308": 10 },
        "max_contains_weight": "1000 kg",
        "max_item_length": "1 km"
      }
    ]
  },
  {
    "type": "MAGAZINE",
    "id": "ar10mag_20rd",
    "copy-from": "ar10mag_20rd",
    "name": { "str": "AR-10 20-round magazine" },
    "pocket_data": [
      {
        "pocket_type": "MAGAZINE",
        "rigid": true,
        "ammo_restriction": { "308": 20 },
        "max_contains_weight": "1000 kg",
        "max_item_length": "1 km"
      }
    ]
  }
]
