[
  {
    "type": "GENERIC",
    "id": "broken_sniper",
    "symbol": ",",
    "color": "green",
    "name": { "str": "broken sniper joe" },
    "category": "other",
    "description": "A broken sniper joe. Much less threatening now that it lies limp on solid ground. Could be gutted for parts.",
    "price": 50000,
    "material": [ "steel", "superalloy" ],
    "weight": "135000 g",
    "volume": "19500 ml",
    "bashing": 6,
    "cutting": 6,
    "to_hit": -6
  },
  {
    "type": "GENERIC",
    "id": "broken_met",
    "symbol": ",",
    "color": "green",
    "name": { "str": "broken met" },
    "category": "other",
    "description": "A broken met. Much less threatening now that it lies limp on solid ground. Could be gutted for parts.",
    "price": 20000,
    "material": [ "steel", "plastic" ],
    "weight": "40000 g",
    "volume": "17500 ml",
    "bashing": 6,
    "cutting": 6,
    "to_hit": -6
  },
  {
    "type": "GENERIC",
    "id": "broken_cyborg",
    "symbol": ",",
    "color": "light_green",
    "name": { "str": "destroyed cyborg" },
    "category": "other",
    "description": "This is a heavily damaged cyborg, composed of a previously dead human, several bionic upgrades, and some limiters and control systems.",
    "price": 600000,
    "material": [ "hflesh", "steel" ],
    "weight": "86700 g",
    "volume": "19250 ml",
    "bashing": 6,
    "cutting": 0,
    "to_hit": -10,
    "max_charges": 0,
    "initial_charges": 0,
    "charges_per_use": 0,
    "turns_per_charge": 0
  },
  {
    "type": "GENERIC",
    "id": "broken_cyborg_heavy",
    "symbol": ",",
    "color": "light_green",
    "name": { "str": "destroyed heavy cyborg" },
    "category": "other",
    "description": "This is a heavily damaged cyborg, sturdy in it's construction, with many pieces of extra hardware attached, and a thick steel skin, covering it's advanced electronics and life sustaining systems. It it's current state, this cyborg is probably less man than machine.",
    "price": 1800000,
    "material": [ "hardsteel", "hflesh" ],
    "weight": "93000 g",
    "volume": "19750 ml",
    "bashing": 8,
    "cutting": 0,
    "to_hit": -12,
    "max_charges": 0,
    "initial_charges": 0,
    "charges_per_use": 0,
    "turns_per_charge": 0
  },
  {
    "type": "GENERIC",
    "id": "broken_cyborg_advanced",
    "symbol": ",",
    "color": "light_green",
    "name": { "str": "destroyed advanced cyborg" },
    "category": "other",
    "description": "A sturdy mechanical body, with little in the way of organic matter visible. It has what appears to be segments of power armor grafted to its skin and steel frame, with cybernetic augmentations protruding.",
    "price": 1950000,
    "material": [ "hardsteel", "hflesh" ],
    "weight": "117000 g",
    "volume": "23250 ml",
    "bashing": 12,
    "cutting": 0,
    "to_hit": -16,
    "max_charges": 0,
    "initial_charges": 0,
    "charges_per_use": 0,
    "turns_per_charge": 0
  }
]
