[
  {
    "id": "hchem_notebook",
    "type": "BOOK",
    "name": { "str": "homeade chemists notebook", "str_pl": "homeade chemists notebooks" },
    "description": "This appears to be a compound of someones notes contained within a compsition book. It features several illistrations and recipies for... serum?",
    "weight": "1 kg",
    "volume": "200 ml",
    "price": 200,
    "bashing": 1,
    "material": [ "paper" ],
    "symbol": "?",
    "color": "red",
    "skill": "cooking",
    "required_level": 1,
    "max_level": 3,
    "intelligence": 9,
    "time": "20 m",
    "fun": 1
  },
  {
    "id": "alchemist",
    "type": "BOOK",
    "name": { "str": "alchemists handbook", "str_pl": "alchemists handbooks" },
    "description": "A small guide, composed for the aspiring alchemist.",
    "weight": "1 kg",
    "volume": "100 ml",
    "price": 1000,
    "bashing": 1,
    "material": [ "paper" ],
    "symbol": "?",
    "color": "pink",
    "skill": "cooking",
    "required_level": 0,
    "max_level": 2,
    "intelligence": 8,
    "time": "20 m",
    "fun": 1
  }
]
