[
  {
    "id": "hvm_004",
    "type": "GUN",
    "copy-from": "shotgun_base",
    "symbol": "(",
    "color": "green",
    "name": { "str": "HVM 004", "str_pl": "HVM 004" },
    "description": "the HVM 004 is the fourth gun, and first shotgun, manufactured by <info>High Value Metrics (HVM)</info>. we are not sure why there isn't a third weapon in the line. \nit's a <color_yellow>very weak shotgun</color> compared to it's competitors, but it's unreal use of some sort of <info>compression or nano technology</info> inside it's chamber makes this shotgun capable of holding up to <good>25 shells</good>, but takes <bad>long to reload</bad>. \nthis shotgun is possibly based on Beneli M4 (due to its famous semi-auto firing capability) with a gunstock grip and very squared green look.\n\nThis weapon is <color_yellow>average</color> and will <good>probably not malfunction</good> and <good>will handle quite the beating.</good>\n\n<info>Xeno's SAS4 Weapons pack Modded Content</info>",
    "price": 25400,
    "material": [ "plastic", "steel" ],
    "skill": "shotgun",
    "ammo": [ "shot" ],
    "longest_side": "1234 mm",
    "barrel_volume": "250 ml",
    "weight": "1200 g",
    "volume": "2500 ml",
    "bashing": 10,
    "to_hit": -2,
    "dispersion": 220,
    "sight_dispersion": 120,
    "min_cycle_recoil": 120,
    "durability": 6,
    "ranged_damage": { "damage_type": "bullet", "amount": -10 },
    "range": -5,
    "clip_size": 1,
    "valid_mod_locations": [
      [ "accessories", 2 ],
      [ "grip", 1 ],
      [ "barrel", 1 ],
      [ "muzzle", 1 ],
      [ "sights", 1 ],
      [ "stock", 1 ],
      [ "underbarrel", 1 ]
    ],
    "flags": [ "NEVER_JAMS", "RELOAD_EJECT" ],
    "pocket_data": [ { "pocket_type": "MAGAZINE", "rigid": true, "ammo_restriction": { "shot": 1 } } ]
  },
  {
    "id": "ria_30_strikeforce",
    "type": "GUN",
    "copy-from": "shotgun_base",
    "symbol": "(",
    "color": "dark_gray",
    "name": { "str": "RIA 30 Strikeforce", "str_pl": "RIA 30 Strikeforce" },
    "description": "the RIA 30 Strikeforce is the only shotgun manufactured by <info>Rubicon Industries</info> \nThe RIA 30 Strikeforce's design is similar to a sawn-off Ithaca 37 shotgun in terms of appearance. It has no front and rear sight and has a handguard that appears to be a shotgun pump on first glance.\n which is not.\n\nThis weapon is <good>good</good> and will <good>probably not malfunction</good> and <good>will handle quite the beating.</good>\n\n<info>Xeno's SAS4 Weapons pack Modded Content</info>",
    "price": 25400,
    "material": [ "plastic", "steel" ],
    "skill": "shotgun",
    "ammo": [ "shot" ],
    "longest_side": "1234 mm",
    "barrel_volume": "250 ml",
    "weight": "1200 g",
    "volume": "2500 ml",
    "bashing": 10,
    "to_hit": -2,
    "dispersion": 220,
    "sight_dispersion": 120,
    "min_cycle_recoil": 180,
    "durability": 6,
    "ranged_damage": { "damage_type": "bullet", "amount": 0 },
    "range": 0,
    "valid_mod_locations": [
      [ "accessories", 2 ],
      [ "grip", 1 ],
      [ "barrel", 1 ],
      [ "muzzle", 1 ],
      [ "sights", 1 ],
      [ "stock", 1 ],
      [ "underbarrel", 1 ]
    ],
    "flags": [ "NEVER_JAMS", "RELOAD_EJECT" ],
    "pocket_data": [
      {
        "pocket_type": "MAGAZINE_WELL",
        "holster": true,
        "max_contains_volume": "20 L",
        "max_contains_weight": "20 kg",
        "item_restriction": [ "saiga10mag", "USAS10mag" ]
      }
    ]
  },
  {
    "id": "stripper",
    "type": "GUN",
    "copy-from": "shotgun_base",
    "symbol": "(",
    "color": "red",
    "name": { "str": "Stripper", "str_pl": "Strippers" },
    "description": "the Stripper is a heavy automatic shotgun manufactured by Rancor, The Stripper is lever action like the 1887 Shockfield (even though the Stripper is still fully automatic, oddly enough)\nthe shotgun has a bayonet like blade under the barrel, but it's small enough so that it's possible to mount an underbarrel modification.\n\nThis weapon is <good>good</good> and will <good>probably not malfunction</good> and <good>will handle quite the beating.</good>\n\n<info>Xeno's SAS4 Weapons pack Modded Content</info>",
    "price": 25400,
    "material": [ "plastic", "steel" ],
    "skill": "shotgun",
    "longest_side": "1234 mm",
    "barrel_volume": "500 ml",
    "ammo": [ "shot" ],
    "weight": "1200 g",
    "volume": "2000 ml",
    "bashing": 18,
    "to_hit": 7,
    "dispersion": 220,
    "sight_dispersion": 120,
    "min_cycle_recoil": 30,
    "durability": 6,
    "ranged_damage": { "damage_type": "bullet", "amount": 10 },
    "range": 3,
    "valid_mod_locations": [ [ "accessories", 2 ], [ "grip", 1 ], [ "muzzle", 1 ], [ "sights", 1 ], [ "stock", 1 ], [ "underbarrel", 1 ] ],
    "flags": "RELOAD_ONE",
    "modes": [ [ "DEFAULT", "semi-auto", 1 ], [ "BURST", "3 rd", 3 ], [ "AUTO", "auto", 7 ] ],
    "pocket_data": [
      {
        "pocket_type": "MAGAZINE_WELL",
        "holster": true,
        "max_contains_volume": "20 L",
        "max_contains_weight": "20 kg",
        "item_restriction": [ "stripper18mag", "stripper18belt" ]
      }
    ]
  }
]
